MANIFEST.in
README.md
setup.cfg
setup.py
examples/microservice_publish_subscribe.py
examples/microservice_publish_subscribe_async_iter.py
examples/microservice_push_pull.py
examples/microservice_request_response.py
examples/requirements.txt
tamarco_amqp/__init__.py
tamarco_amqp/connection.py
tamarco_amqp/input.py
tamarco_amqp/output.py
tamarco_amqp/resource.py
tamarco_amqp/settings.py
tamarco_amqp.egg-info/PKG-INFO
tamarco_amqp.egg-info/SOURCES.txt
tamarco_amqp.egg-info/dependency_links.txt
tamarco_amqp.egg-info/not-zip-safe
tamarco_amqp.egg-info/requires.txt
tamarco_amqp.egg-info/top_level.txt
tests/__init__.py
tests/functional/__init__.py
tests/functional/conftest.py
tests/functional/test_connection.py
tests/functional/test_input.py
tests/functional/test_output.py
tests/functional/test_resource.py
tests/unit/__init__.py
tests/unit/test_connection.py